dir_clean/__init__.py
dir_clean/__main__.py
dir_clean/dir_clean.py
dir_clean-0.1.4.dist-info/LICENSE
dir_clean-0.1.4.dist-info/METADATA
dir_clean-0.1.4.dist-info/WHEEL
dir_clean-0.1.4.dist-info/top_level.txt
dir_clean-0.1.4.dist-info/RECORD
