Metadata-Version: 2.1
Name: dir-clean
Version: 0.1.4
Summary: This package can help you to clean up the directory.
Author-email: DDGG <ddcatgg@gmail.com>
License: MIT License        
Project-URL: Homepage, https://github.com/ddcatgg/dir_clean
Project-URL: Bug Tracker, https://github.com/ddcatgg/dir_clean/issues
Keywords: run,tool
Classifier: Programming Language :: Python :: 2
Classifier: Programming Language :: Python :: 3
Classifier: License :: OSI Approved :: MIT License
Classifier: Operating System :: OS Independent
Requires-Python: >=2.7,>=3.6
License-File: LICENSE
